jplankton.project_manager.shunt-0.1.1.data/scripts/jplankton.project-manager.shunt
jplankton.project_manager.shunt-0.1.1.dist-info/DESCRIPTION.rst
jplankton.project_manager.shunt-0.1.1.dist-info/METADATA
jplankton.project_manager.shunt-0.1.1.dist-info/RECORD
jplankton.project_manager.shunt-0.1.1.dist-info/WHEEL
jplankton.project_manager.shunt-0.1.1.dist-info/metadata.json
jplankton.project_manager.shunt-0.1.1.dist-info/top_level.txt
shunt/__init__.py
shunt/hmap.py
shunt/logutils.py
shunt/project_paths.py
shunt/shunt.py
shunt/shuntfile.py
