Metadata-Version: 2.0
Name: jplankton.project-manager.shunt
Version: 0.1.1
Summary: Materialize a set of Jinja2 template files to "shunt" a project into place as a starting point
Home-page: https://github.com/velezj/project-manager
Author: Javier Velez
Author-email: javier@salientlore.ml
License: MIT
Platform: UNKNOWN
Classifier: Development Status :: 3 - Alpha
Classifier: License :: OSI Approved :: MIT License
Classifier: Programming Language :: Python :: 3.6
Requires-Dist: jinja2
Requires-Dist: pyyaml
